LICENSE.txt
setup.cfg
setup.py
kerenor/__init__.py
kerenor/__main__.py
kerenor/run.py
kerenor/states.py
kerenor.egg-info/PKG-INFO
kerenor.egg-info/SOURCES.txt
kerenor.egg-info/dependency_links.txt
kerenor.egg-info/top_level.txt
kerenor/imgs/no.png
kerenor/imgs/thought.png
kerenor/imgs/what.png
kerenor/imgs/zen.png