Metadata-Version: 2.1
Name: kerenor
Version: 0.1.0
Summary: kerenor
Author: kerenor
License-File: LICENSE.txt
